setuptools_node/__init__.py
setuptools_node/gulp.py
setuptools_node/node.py
setuptools_node/util.py
setuptools_node-0.3.0.dist-info/LICENSE.md
setuptools_node-0.3.0.dist-info/METADATA
setuptools_node-0.3.0.dist-info/WHEEL
setuptools_node-0.3.0.dist-info/top_level.txt
setuptools_node-0.3.0.dist-info/RECORD
