Metadata-Version: 2.1
Name: setuptools-node
Version: 0.3.0
Summary: Setuptools extensions for working with node
Home-page: https://github.com/dj51d/setuptools-node
Author: Dan Johnson
Author-email: dj51d@warbirdsurvivors.com
Classifier: Development Status :: 4 - Beta
Classifier: Intended Audience :: Developers
Classifier: Topic :: Software Development :: Build Tools
Classifier: License :: OSI Approved :: MIT License
Classifier: Programming Language :: Python :: 3.6
Classifier: Programming Language :: Python :: 3.7
Classifier: Programming Language :: Python :: 3.8
Requires-Python: >=3.6
License-File: LICENSE.md
Requires-Dist: setuptools (>=65.5.1)
